{"airship":{"bgm":{"name":"Ship3","pan":0,"pitch":100,"volume":90},"characterIndex":3,"characterName":"Vehicle","startMapId":0,"startX":0,"startY":0},"armorTypes":["","Cloth Armor","Wristbands","Light Armor","Heavy Armor","Small Shield","Large Shield","Ring"],"attackMotions":[{"type":0,"weaponImageId":0},{"type":0,"weaponImageId":1},{"type":1,"weaponImageId":2},{"type":1,"weaponImageId":24},{"type":1,"weaponImageId":4},{"type":1,"weaponImageId":17},{"type":1,"weaponImageId":6},{"type":2,"weaponImageId":7},{"type":0,"weaponImageId":1},{"type":2,"weaponImageId":9},{"type":0,"weaponImageId":10},{"type":1,"weaponImageId":4},{"type":0,"weaponImageId":12},{"type":1,"weaponImageId":2},{"type":1,"weaponImageId":14},{"type":0,"weaponImageId":1},{"type":1,"weaponImageId":17},{"type":1,"weaponImageId":3}],"battleBgm":{"name":"Battle1","pan":0,"pitch":100,"volume":90},"battleback1Name":"Clouds","battleback2Name":"Clouds","battlerHue":0,"battlerName":"Actor1_3","boat":{"bgm":{"name":"Ship1","pan":0,"pitch":100,"volume":90},"characterIndex":7,"characterName":"Vehicle","startMapId":0,"startX":0,"startY":0},"currencyUnit":"Gold","defeatMe":{"name":"Defeat1","pan":0,"pitch":100,"volume":90},"editMapId":46,"elements":["","\\i[1648]Physical","\\i[1344]Fire","\\i[1345]Ice","\\i[1347]Thunder","\\i[1348]Water","\\i[1349]Earth","\\i[1346]Wind","\\i[1351]Light","\\i[1350]Dark","\\i[1477]Ranged"],"equipTypes":["","Main Hand","Off Hand","Headgear","Body Armor","Ring","Ring"],"gameTitle":"Hour of Fate: Sins of Alabathia","gameoverMe":{"name":"Gameover3","pan":0,"pitch":100,"volume":90},"locale":"en_US","magicSkills":[3,4,9],"menuCommands":[true,true,true,true,true,true],"optDisplayTp":true,"optDrawTitle":true,"optExtraExp":false,"optFloorDeath":false,"optFollowers":true,"optSideView":true,"optSlipDeath":true,"optTransparent":true,"partyMembers":[1],"ship":{"bgm":{"name":"Ship2","pan":0,"pitch":100,"volume":90},"characterIndex":1,"characterName":"Vehicle","startMapId":0,"startX":0,"startY":0},"skillTypes":["","Survival Tactics","Aim","White Magic","Black Magic","Blood Rage","Holy Sword","Stealth","Load","Astrology","Battle Cry","Sins Powers","Zornhau","Ultimate Attacks","Geomancy","Field Dressings","Meditation","Dragon Call","Ninjitsu","Bushido"],"sounds":[{"name":"Cursor1","pan":0,"pitch":100,"volume":90},{"name":"Decision2","pan":0,"pitch":100,"volume":90},{"name":"Cancel2","pan":0,"pitch":100,"volume":90},{"name":"Buzzer3_A","pan":0,"pitch":100,"volume":90},{"name":"Equip2","pan":0,"pitch":100,"volume":90},{"name":"Save","pan":0,"pitch":100,"volume":90},{"name":"Load","pan":0,"pitch":100,"volume":90},{"name":"Crash","pan":0,"pitch":100,"volume":90},{"name":"Run","pan":0,"pitch":100,"volume":90},{"name":"Attack3","pan":0,"pitch":100,"volume":90},{"name":"Damage5","pan":0,"pitch":100,"volume":90},{"name":"Collapse1","pan":0,"pitch":100,"volume":90},{"name":"Collapse2","pan":0,"pitch":80,"volume":90},{"name":"Collapse3","pan":0,"pitch":100,"volume":90},{"name":"Damage2","pan":0,"pitch":100,"volume":90},{"name":"Collapse4","pan":0,"pitch":100,"volume":90},{"name":"Recovery","pan":0,"pitch":100,"volume":90},{"name":"Miss","pan":0,"pitch":100,"volume":90},{"name":"Evasion1","pan":0,"pitch":100,"volume":90},{"name":"Evasion2","pan":0,"pitch":100,"volume":90},{"name":"Reflection","pan":0,"pitch":100,"volume":90},{"name":"Shop2","pan":0,"pitch":100,"volume":90},{"name":"Item2","pan":0,"pitch":100,"volume":90},{"name":"Item3","pan":0,"pitch":100,"volume":90}],"startMapId":33,"startX":7,"startY":5,"switches":["","Ice Golem Defeated","Leo in party","Gate of greed open","Charity speaks","Charity awakes","greed death","Charity teleports","Charity gone","unlock warrior","First mission","Scan","mission text end","Sin 1 defeated","Leo tossed","Leo falls","Leo's story","Demon story ","EXP ring acquired","Platar Burned","Item dropped","World Map","Envy appears","Dead Rise CS activate","Envy Gate Cutscene Switch","Game Start","North Mountain CS","Envy gate opens1","Envy Gate opens2","After the ball","Envy Death","Zagolia Reunited","Dio uses crystal","Lust appears","Purity warps","Purity appears","Lust warped","Lust falls","Arrive in Gerogina","Opening sequence","Celebration","Cyran appears","Beginner's Hall skipped","Quest for the priestess","greed appears","Forbidden mountain open","Game over Greed sequence","greed game over 2","Black King defeated","Flag for Greed cutscene","Cyran defeated","","","","","","","","","","","Prison door opens","Prison door 2 opens","Remove leo prison","endrolphia pt 2 init","Desmond","desmond leaves","Endrolphia cutscene 1","Endrolphia cutscene 2 ","Basement 2 big room saved","Basement 2 single saved","Basement 3 sundries","Basement 3 library","Kingdom rejoined","Prince spoken to ","Gerogina cs done","underground passage gerogina","CS flag Endrolphia","North Mountain CS","Glacier CS1","","The last dragoon","Monsters cleared","Dragoon quest","Aegis Acquired","medusa defeated","Elf's final Cutscene","Close shrine door","","","","","","","","","","","","","Beast Book","Gilgamesh","secret door ashton","greg battle chat","Rank Delta","Rank Echo","Registration","The Pit Door","Rank Charlie","Rank Beta","Rank Alpha","Rank BattleMaster","E-9 Victory","E-10 Victory","","","","","","","","Pyramid open","Gluttony Appears","Viktoria killed","Astrologist quest","Light gathered","","","","","","","","","","","","","","","","BEES! quest switch","Aqua-glean quest switch","Dye quest Switch","David arrested","Steve arrested","Lee arrested","Sandra arrested","Mary arrested","sandra interrogated","Lee interrogated","steve interrogated","?Mary interrogated","David interrogated","Dye quest complete","","","","","","","","","","","","","","","","","","","","","","","","","","","","","","","","","","","","","","","","","","","","","Ultimate weapon gathered","New Game Plus","desmond below 25%HP","Viktoria below 25%HP","Cyran below 25%","Seth below 25%","Howl attack","Howl magic","Excalibur Acquired","BGM Endrolphia prison escape","","","","","","","","","","","","","Cameron Job","","","","","","","","","","","","","","","","","","","","","","","","","","","","","","","","","","","","","","","","","","","","","","","","","","","","","","","","","","","","","","","","","","","","","","","","","","","","","","","","Platar Destination","Academy Destination","Class change quest","Subclass quest","Rescue Quest","To Endrolphia","Off to Wistery","The Light Temple","Under The Mountains","The Forbidden Mountain","The Gate of Greed","des cave cs","Beginner's Hall dest","Job board plat dest","Return to the King","Off to Geregina","The Medallion","The Medallion Pt. 2","Glacier Run","Beyond the Glacier","","","","","","","","","","","","","","","","","","","","","","","","","","","","","","","","","","","","","","","","","","","","","","","","","","","","","","","","","","","","","","","","","","","","","","","","","","","","","","","","","Dawn 5am-7am","Morning 8am-11am","Day 12pm-2pm","Afternoon 3pm-5pm","Evening 6pm-9pm","Night 10pm-4am","","","Monday","Tuesday","Wednesday","Thursday","Friday","Saturday","Sunday","January","February","March","April","May","June","July","August","September","October","November","December","Winter","Spring","Summer","Fall","","","","","","","","","","","","","","","","","","","","","","","","","","","","","","","","","","","","","","","","","","","","","","","","","","","","","","","","","","","","","","","","","","","","","test switch"],"terms":{"basic":["Level","Lv","Health Points","HP","Magick Points","MP","Technique Points","TP","Experience","EXP"],"commands":["Fight","Escape","Attack","Guard","Item","Skill","Equip","Status","Formation","Save","Game End","Options","Weapon","Armor","Key Item","Equip","Optimize","Empty","New Game","Load",null,"Exit to main menu","Cancel",null,"Buy","Sell"],"params":["Max HP","Max MP","Strength","Vitality","Will","Spirit","Speed","Luck","Accuracy","Evasion "],"messages":{"actionFailure":"There was no effect on %1!","actorDamage":"%1 took %2 damage!","actorDrain":"%1 was drained of %2 %3!","actorGain":"%1 gained %2 %3!","actorLoss":"%1 lost %2 %3!","actorNoDamage":"%1 took no damage!","actorNoHit":"Miss! %1 took no damage!","actorRecovery":"%1 recovered %2 %3!","alwaysDash":"Always Run","bgmVolume":"Background Music","bgsVolume":"Background Sound","buffAdd":"%1's %2 went up!","buffRemove":"%1's %2 returned to normal!","commandRemember":"Remember Last Command","counterAttack":"%1 counterattacked!","criticalToActor":"A painful blow!!","criticalToEnemy":"An excellent hit!!","debuffAdd":"%1's %2 went down!","defeat":"%1 was defeated.","emerge":"%1 emerged!","enemyDamage":"%1 took %2 damage!","enemyDrain":"%1 was drained of %2 %3!","enemyGain":"%1 gained %2 %3!","enemyLoss":"%1 lost %2 %3!","enemyNoDamage":"%1 took no damage!","enemyNoHit":"Miss! %1 took no damage!","enemyRecovery":"%1 recovered %2 %3!","escapeFailure":"However, was unable to escape!","escapeStart":"%1 has started to escape!","evasion":"%1 evaded the attack!","expNext":"To Next %1","expTotal":"Current %1","file":"File","levelUp":"%1 is now %2 %3!","loadMessage":"Load which file?","magicEvasion":"%1 nullified the magic!","magicReflection":"%1 reflected the magic!","meVolume":"Music Effects","obtainExp":"%1 %2 received!","obtainGold":"%1\\Platinum found!","obtainItem":"%1 found!","obtainSkill":"%1 learned!","partyName":"%1's Party","possession":"Possession","preemptive":"%1 got the upper hand!","saveMessage":"Save to which file?","seVolume":"Sound Effects","substitute":"%1 protected %2!","surprise":"%1 was surprised!","useItem":"%1 uses %2!","victory":"%1 was victorious!"}},"testBattlers":[{"actorId":1,"equips":[47,0,47,57,83,0],"level":99},{"actorId":2,"equips":[37,0,67,77,83,null],"level":99},{"actorId":3,"equips":[157,0,26,37,97,null],"level":99},{"actorId":4,"equips":[9,14,67,77,88,null],"level":99}],"testTroopId":48,"title1Name":"Dragon","title2Name":"","titleBgm":{"name":"TalesofExcitement","pan":0,"pitch":100,"volume":90},"variables":["","Legendary Weapon Count","Optional Bosses Defeated","Sins Cleansed","High level Bosses Defeated","Shards collected","Chests opened","region ID (weather)","Map ID","Warrior Zombie","Vampire Lord","Baby dragons fed","Points touched","Information in Saxondale","Zagolia Engineers","Map","\\i[2288]Honor Coins","Outdoor Region","Kill Counter","Player X (weather)","Player Y (weather)","Flashbacks","Minute","Hour","Day ","Month","Year","Region","Weather","Seconds","Sidequest completed","System time","","map change X","map change Y","map ID","Game over images","Game over music","","","","Dexterity","Class Change from X to Arch","BEES variable","Wistery Suspects","","","","","","","","","","","","","","","","","Glory","Draw","","","","","","","","","","","","","","","","","","","","","","","","","","","","","","","","","","","","","","Hand of the White Mage recovery","Hand of the Black Mage recovery","Hagakure TP transfer","Seth Randomizer","","","","","","","","","","","","","","","","","","","","","","","","","","","","","","","","","","","","","","","","","","","","","","","","","","","","","","","","","","","","","","","","","","","","","","","","","","","","","","Hell Howl","","","","","","","","","","","","","","","","","","Pre title skip","Enemies Discovered"],"versionId":37891781,"victoryMe":{"name":"Victory1","pan":0,"pitch":100,"volume":90},"weaponTypes":["","Dagger","Sword","Book","Rapier","Great Katana","Cane","Bow","Katana","Gun","Claw","Great Axe","Spear","Great Sword","Staff"],"windowTone":[-255,-255,-255,0]}